zsh_tool/__init__.py
zsh_tool/alan.py
zsh_tool/config.py
zsh_tool/neverhang.py
zsh_tool/server.py
zsh_tool/tasks.py
zsh_tool_mcp-0.4.81.dist-info/METADATA
zsh_tool_mcp-0.4.81.dist-info/WHEEL
zsh_tool_mcp-0.4.81.dist-info/entry_points.txt
zsh_tool_mcp-0.4.81.dist-info/licenses/LICENSE
zsh_tool_mcp-0.4.81.dist-info/RECORD
