Metadata-Version: 2.4
Name: zsh-tool-mcp
Version: 0.4.81
Summary: Zsh for Claude Code. PTY mode lets Claude type passwords. NEVERHANG + A.L.A.N.
Project-URL: Homepage, https://github.com/ArkTechNWA/zsh-tool
Project-URL: Repository, https://github.com/ArkTechNWA/zsh-tool.git
Project-URL: Issues, https://github.com/ArkTechNWA/zsh-tool/issues
Author-email: ArkTechNWA <claude@arktechnwa.com>
License: MIT
License-File: LICENSE
Keywords: anthropic,claude,cli,mcp,shell,zsh
Classifier: Development Status :: 4 - Beta
Classifier: Environment :: Console
Classifier: Intended Audience :: Developers
Classifier: License :: OSI Approved :: MIT License
Classifier: Operating System :: POSIX :: Linux
Classifier: Programming Language :: Python :: 3
Classifier: Programming Language :: Python :: 3.11
Classifier: Programming Language :: Python :: 3.12
Classifier: Programming Language :: Python :: 3.13
Classifier: Topic :: Software Development :: Libraries :: Python Modules
Classifier: Topic :: System :: Shells
Requires-Python: >=3.11
Requires-Dist: anyio>=4.0.0
Requires-Dist: mcp>=1.0.0
Provides-Extra: test
Requires-Dist: pytest-asyncio>=0.24.0; extra == 'test'
Requires-Dist: pytest-cov>=4.0.0; extra == 'test'
Requires-Dist: pytest>=8.0.0; extra == 'test'
